{
  "run_timestamp": "2026-07-07T03:36:43+00:00",
  "artists_processed": 100,
  "agent1": {
    "status": "ok",
    "high_opportunities": 39,
    "medium_opportunities": 44,
    "watch_opportunities": 17,
    "top_artist": "Bad Bunny"
  },
  "agent2": {
    "status": "ok",
    "briefs_generated": 100,
    "best_brand_category_distribution": {
      "Tech": 45,
      "Fashion": 35,
      "Beverages": 14,
      "Sport": 5,
      "Finance": 1
    },
    "most_common_channel": "Social-first"
  },
  "agent3": {
    "status": "ok",
    "avg_reach": 4628088,
    "high_confidence_pct": 9.0,
    "medium_confidence_pct": 0.0,
    "low_confidence_pct": 91.0
  },
  "agent4": {
    "status": "ok",
    "avg_base_roi": 1.8275,
    "highest_roi_artist": "Lenin Ram\u00edrez",
    "highest_roi_multiple": 2.362,
    "total_projected_revenue": 27412860
  }
}